CalSim/__init__.py
CalSim/core/__init__.py
CalSim/core/control.py
CalSim/core/controller.py
CalSim/core/depth_cam.py
CalSim/core/dynamics.py
CalSim/core/environment.py
CalSim/core/exceptions.py
CalSim/core/hybrid_domain.py
CalSim/core/manipulator.py
CalSim/core/obstacle.py
CalSim/core/run_simulation.py
CalSim/core/sim_utils.py
CalSim/core/state_estimation.py
CalSim/core/tests.py
CalSim/core/transforms.py
CalSim/core/twist.py
CalSim/tests/test_3d_depth_cam.py
CalSim/tests/test_3d_qrotor.py
CalSim/tests/test_discrete.py
CalSim/tests/test_double_pend.py
CalSim/tests/test_hybrid.py
CalSim/tests/test_planar_depth_cam.py
CalSim/tests/test_planar_qrotor.py
CalSim/tests/test_tiltrotor.py
calsim-0.0.22.dist-info/METADATA
calsim-0.0.22.dist-info/WHEEL
calsim-0.0.22.dist-info/licenses/LICENSE
calsim-0.0.22.dist-info/RECORD
