Metadata-Version: 2.3
Name: CalSim
Version: 0.0.22
Summary: Simulator package for Berkeley robotics course.
Project-URL: Homepage, https://github.com/mzdesa/CalSim
Project-URL: Bug Tracker, https://github.com/mzdesa/CalSim
Author-email: Massimiliano de Sa <mz.desa@berkeley.edu>
License-File: LICENSE
Classifier: License :: OSI Approved :: MIT License
Classifier: Operating System :: OS Independent
Classifier: Programming Language :: Python :: 3
Requires-Python: >=3.7
Requires-Dist: matplotlib>=3.5.0
Requires-Dist: numpy>=1.20.0
Requires-Dist: seaborn>=0.10.0
